LICENSE
nv/__init__.py
nv/nfe/__init__.py
nv/nfe/core.py
nv/nfe/parser.py
nv_nfe-0.1.0a1.dist-info/LICENSE
nv_nfe-0.1.0a1.dist-info/WHEEL
nv_nfe-0.1.0a1.dist-info/METADATA
nv_nfe-0.1.0a1.dist-info/RECORD
