Metadata-Version: 2.1
Name: nv-nfe
Version: 0.1.0a1
Summary: Simple XML parser for reading standard Brazilian digital invoices (NFe)
Home-page: https://github.com/gstos/nv-nfe
License: MIT
Author: Gustavo Santos
Author-email: gustavo@next.ventures
Requires-Python: >=3.9,<4.0
Classifier: License :: OSI Approved :: MIT License
Classifier: Operating System :: OS Independent
Classifier: Programming Language :: Python :: 3
Classifier: Programming Language :: Python :: 3.9
Classifier: Topic :: Software Development :: Libraries :: Python Modules
Requires-Dist: dicttoxml (>=1.7.4,<2.0.0)
Requires-Dist: nv-utils (>=0.2.0a2,<0.3.0)
Requires-Dist: xmltodict (>=0.12.0,<0.13.0)
Project-URL: Repository, https://github.com/gstos/nv-nfe
